orangecontrib/__init__.py
orangecontrib/blue_whale/__init__.py
orangecontrib/blue_whale/canvasmain.py
orangecontrib/blue_whale/i18n_config.py
orangecontrib/blue_whale/locale/bluewhale.de.yml
orangecontrib/blue_whale/locale/bluewhale.en.yml
orangecontrib/blue_whale/locale/bluewhale.zh.yml
orangecontrib/blue_whale/widgets/__init__.py
orangecontrib/blue_whale/widgets/owcase.py
orangecontrib/blue_whale/widgets/owcasedata.py
orangecontrib/blue_whale/widgets/user
orangecontrib/blue_whale/widgets/datasets/60125a7df3819b04d795b7c0.sqlite
orangecontrib/blue_whale/widgets/datasets/6012a692f3819b04d795b82d.xlsx
orangecontrib/blue_whale/widgets/datasets/6012bbc4f3819b04d795b841.sqlite
orangecontrib/blue_whale/widgets/datasets/6012bc1ff3819b04d795b846.sqlite
orangecontrib/blue_whale/widgets/datasets/6012bd80f3819b04d795b852.sqlite
orangecontrib/blue_whale/widgets/datasets/6012bedef3819b04d795b869.sqlite
orangecontrib/blue_whale/widgets/datasets/605200d868ab6e74bd042d32.sqlite
orangecontrib/blue_whale/widgets/datasets/60814a7a1b6e627a7fc8cfe9.sqlite
orangecontrib/blue_whale/widgets/datasets/60853fa7746e3b6ef8e8f90b.sqlite
orangecontrib/blue_whale/widgets/datasets/609b77529433c2711874a98d.sqlite
orangecontrib/blue_whale/widgets/datasets/617d0a116ea8087df8bae0e5.sqlite
orangecontrib/blue_whale/widgets/icons/bw.svg
orangecontrib/blue_whale/widgets/icons/case.svg
orangecontrib/blue_whale/widgets/icons/data.svg
orangecontrib/blue_whale/widgets/icons/login-bg.jpg
orangecontrib/blue_whale/widgets/icons/login-bg.png
orangecontrib/blue_whale/widgets/utils/__init__.py
orangecontrib/blue_whale/widgets/utils/config.py
orangecontrib/blue_whale/widgets/utils/local_file.py
orangecontrib/blue_whale/widgets/utils/login.py
orangecontrib/blue_whale/widgets/utils/remote.py
orangecontrib/blue_whale/widgets/utils/service_window.py
Blauwal3_Bluewhale-0.0.56.dist-info/METADATA
Blauwal3_Bluewhale-0.0.56.dist-info/WHEEL
Blauwal3_Bluewhale-0.0.56.dist-info/entry_points.txt
Blauwal3_Bluewhale-0.0.56.dist-info/top_level.txt
Blauwal3_Bluewhale-0.0.56.dist-info/RECORD
