Metadata-Version: 2.1
Name: Blauwal3-Bluewhale
Version: 0.0.56
Summary: 蓝鲸大数据平台，提供教学数据与案例
Home-page: https://bw.dashenglab.com/
Author: 大数据团队
Author-email: dashenglab@163.com
License: BlueWhale
Classifier: Development Status :: 1 - Planning
Classifier: Environment :: X11 Applications :: Qt
Classifier: Programming Language :: Python :: 3
Classifier: Operating System :: OS Independent
Classifier: Topic :: Scientific/Engineering :: Visualization
Classifier: Topic :: Software Development :: Libraries :: Python Modules
Classifier: Intended Audience :: Education
Classifier: Intended Audience :: Developers
Requires-Dist: requests
Requires-Dist: PyQt5
Requires-Dist: AnyQt
Requires-Dist: numpy>=1.26.4
Requires-Dist: setuptools
Requires-Dist: Blauwal3-Canvas-Core
Requires-Dist: Blauwal3-Widget-Base
Requires-Dist: Blauwal3
Requires-Dist: python-i18n
